.flake8
AUTHORS.rst
CHANGES.rst
CONTRIBUTING.rst
LICENSE
MANIFEST.in
README.rst
pytest.ini
run-tests.sh
setup.cfg
setup.py
tox.ini
docs/conf.py
docs/index.rst
docs/requirements.txt
pytest_reana/__init__.py
pytest_reana/fixtures.py
pytest_reana/plugin.py
pytest_reana/test_utils.py
pytest_reana/version.py
pytest_reana.egg-info/PKG-INFO
pytest_reana.egg-info/SOURCES.txt
pytest_reana.egg-info/dependency_links.txt
pytest_reana.egg-info/entry_points.txt
pytest_reana.egg-info/not-zip-safe
pytest_reana.egg-info/requires.txt
pytest_reana.egg-info/top_level.txt
pytest_reana/test_workspace/code/worldpopulation.ipynb
pytest_reana/test_workspace/data/World_historical_and_predicted_populations_in_percentage.csv
tests/conftest.py
tests/test_fixtures.py
tests/test_version.py